{
    "id":42,
    "name": "pharaos",
    "cardWidth":5,
    "cardHeight":3,
    "numPerCard":15,
    "availableBalls":60,
    "maxPrizeValue":1000,
	"pattern": [{
		"name": "bingo",
		"alias": "P01",
		"format": "111111111111111",
		"value": 1000,
		"r": 1,
		"weight": 0,
		"is_eb": true
	},
	{
		"name": "3_sides",
		"alias": "P02",
		"format": "111101100111111",
		"value": 200,
		"r": 1,
		"weight": 0,
		"is_eb": true
	},
	{
		"name": "2_sides",
		"alias": "P03",
		"format": "110100100011111",
		"value": 70,
		"r": 1,
		"weight": 0,
		"is_eb": true
	},
	{
		"name": "2_sides",
		"alias": "P04",
		"format": "101001000111111",
		"value": 70,
		"r": 1,
		"weight": 0,
		"is_eb": true
	},
	{
		"name": "2_sides",
		"alias": "P05",
		"format": "111101100110001",
		"value": 70,
		"r": 1,
		"weight": 0,
		"is_eb": true
	}
	,
	{
		"name": "1_side",
		"alias": "P06",
		"format": "110100100010000",
		"value": 4,
		"r": -1,
		"weight": 0,
		"is_eb": false
	}
	,
	{
		"name": "1_side",
		"alias": "P06",
		"format": "101001000100001",
		"value": 4,
		"r": -1,
		"weight": 0,
		"is_eb": false
	}
	,
	{
		"name": "1_side",
		"alias": "P06",
		"format": "000000000011111",
		"value": 4,
		"r": -1,
		"weight": 0,
		"is_eb": false
	}
	]
}